{"lattice": {"a": 4.17469099, "c": 26.649162, "b": 5.5706348, "matrix": [[4.17469099, 0.0, 0.0], [0.0, 5.5706348, 0.0], [0.0, 0.0, 26.649162]], "volume": 619.744354643018, "beta": 90.0, "alpha": 90.0, "gamma": 90.0}, "sites": [{"label": "Er", "xyz": [2.087345495, 0.0, 12.1779035355087], "abc": [0.5, -0.0, 0.45697135], "species": [{"occu": 1, "element": "Er"}], "properties": {"magmom": -0.0}}, {"label": "Er", "xyz": [0.0, 2.7853174, 14.471258464491301], "abc": [-0.0, 0.5, 0.54302865], "species": [{"occu": 1, "element": "Er"}], "properties": {"magmom": -0.0}}, {"label": "Se", "xyz": [2.087345495, 2.7853174, 12.541092972283801], "abc": [0.5, 0.5, 0.47059989999999996], "species": [{"occu": 1, "element": "Se"}], "properties": {"magmom": 0.0}}, {"label": "Se", "xyz": [0.0, 0.0, 14.108069027716201], "abc": [0.0, 0.0, 0.5294000999999999], "species": [{"occu": 1, "element": "Se"}], "properties": {"magmom": 0.0}}, {"label": "I", "xyz": [0.0, 0.0, 10.009804997758499], "abc": [-0.0, 0.0, 0.37561425], "species": [{"occu": 1, "element": "I"}], "properties": {"magmom": -0.0}}, {"label": "I", "xyz": [2.087345495, 2.7853174, 16.6393570022415], "abc": [0.5, 0.5, 0.62438575], "species": [{"occu": 1, "element": "I"}], "properties": {"magmom": -0.0}}], "@class": "Structure", "@module": "pymatgen.core.structure"}