{"lattice": {"a": 4.26442546, "c": 26.487177, "b": 4.26504967, "matrix": [[4.26442546, 0.0, 0.0], [0.0, 4.26504967, 0.0], [0.0, 0.0, 26.487177]], "volume": 481.7484150745649, "beta": 90.0, "alpha": 90.0, "gamma": 90.0}, "sites": [{"label": "Bi", "xyz": [0.0, 4.258386937357016, 10.7161979629662], "abc": [0.0, 0.99843783, 0.40458059999999996], "species": [{"occu": 1, "element": "Bi"}], "properties": {"magmom": 0.0}}, {"label": "Bi", "xyz": [0.0, 0.006662732642983, 15.7709790370338], "abc": [-0.0, 0.00156217, 0.5954193999999999], "species": [{"occu": 1, "element": "Bi"}], "properties": {"magmom": 0.0}}, {"label": "Te", "xyz": [2.13221273, 2.13917029419182, 16.77848079422298], "abc": [0.5, 0.50155812, 0.63345674], "species": [{"occu": 1, "element": "Te"}], "properties": {"magmom": -0.0}}, {"label": "Te", "xyz": [2.13221273, 2.125879375808179, 9.708696205777018], "abc": [0.5, 0.49844188, 0.36654326], "species": [{"occu": 1, "element": "Te"}], "properties": {"magmom": -0.0}}, {"label": "S", "xyz": [0.0, 0.0, 13.2435885], "abc": [-0.0, -0.0, 0.5], "species": [{"occu": 1, "element": "S"}], "properties": {"magmom": -0.0}}], "@class": "Structure", "@module": "pymatgen.core.structure"}