{"lattice": {"a": 6.61714589, "c": 22.81543, "b": 6.56602734, "matrix": [[6.61714589, 0.0, 0.0], [0.0, 6.56602734, 0.0], [0.0, 0.0, 22.81543]], "volume": 991.2930350519497, "beta": 90.0, "alpha": 90.0, "gamma": 90.0}, "sites": [{"label": "Na", "xyz": [3.308572945, 0.0, 12.119026869869698], "abc": [0.5, -0.0, 0.5311767900000001], "species": [{"occu": 1, "element": "Na"}], "properties": {"magmom": 0.0}}, {"label": "Na", "xyz": [0.0, 3.28301367, 10.6964031301303], "abc": [0.0, 0.5, 0.46882321], "species": [{"occu": 1, "element": "Na"}], "properties": {"magmom": 0.0}}, {"label": "B", "xyz": [3.308572945, 3.28301367, 11.9924991115644], "abc": [0.5, 0.5, 0.52563108], "species": [{"occu": 1, "element": "B"}], "properties": {"magmom": 0.0}}, {"label": "B", "xyz": [0.0, 0.0, 10.8229308884356], "abc": [0.0, -0.0, 0.47436892], "species": [{"occu": 1, "element": "B"}], "properties": {"magmom": 0.0}}, {"label": "F", "xyz": [2.158506901543781, 3.28301367, 11.1658830778693], "abc": [0.32619908000000003, 0.5, 0.48940051], "species": [{"occu": 1, "element": "F"}], "properties": {"magmom": 0.0}}, {"label": "F", "xyz": [5.467079846543781, 0.0, 11.6495469221307], "abc": [0.82619908, -0.0, 0.51059949], "species": [{"occu": 1, "element": "F"}], "properties": {"magmom": 0.0}}, {"label": "F", "xyz": [4.458638988456219, 3.28301367, 11.1658830778693], "abc": [0.67380092, 0.5, 0.48940051], "species": [{"occu": 1, "element": "F"}], "properties": {"magmom": 0.0}}, {"label": "F", "xyz": [1.150066043456218, 0.0, 11.6495469221307], "abc": [0.17380092, -0.0, 0.51059949], "species": [{"occu": 1, "element": "F"}], "properties": {"magmom": 0.0}}, {"label": "F", "xyz": [0.0, 5.410394774971061, 10.0174118265529], "abc": [0.0, 0.8239982100000001, 0.43906303], "species": [{"occu": 1, "element": "F"}], "properties": {"magmom": 0.0}}, {"label": "F", "xyz": [3.308572945, 4.438646235028939, 12.7980181734471], "abc": [0.5, 0.67600179, 0.56093697], "species": [{"occu": 1, "element": "F"}], "properties": {"magmom": 0.0}}, {"label": "F", "xyz": [0.0, 1.155632565028938, 10.0174118265529], "abc": [-0.0, 0.17600179, 0.43906303], "species": [{"occu": 1, "element": "F"}], "properties": {"magmom": 0.0}}, {"label": "F", "xyz": [3.308572945, 2.127381104971061, 12.7980181734471], "abc": [0.5, 0.32399821, 0.56093697], "species": [{"occu": 1, "element": "F"}], "properties": {"magmom": 0.0}}], "@class": "Structure", "@module": "pymatgen.core.structure"}