{"lattice": {"a": 5.77169157, "c": 22.503776, "b": 8.17198926, "matrix": [[5.77169157, 0.0, 0.0], [-0.0, 8.17198926, 0.0], [0.0, 0.0, 22.503776]], "volume": 1061.4176338235793, "beta": 90.0, "alpha": 90.0, "gamma": 90.0}, "sites": [{"label": "Li", "xyz": [4.328768677499999, 2.91948998863346, 11.251888], "abc": [0.75, 0.35725573, 0.5], "species": [{"occu": 1, "element": "Li"}], "properties": {"magmom": -0.001}}, {"label": "Li", "xyz": [1.4429228925, 5.25249927136654, 11.251888], "abc": [0.25, 0.64274427, 0.5], "species": [{"occu": 1, "element": "Li"}], "properties": {"magmom": -0.001}}, {"label": "Ni", "xyz": [2.885845785, 0.0, 11.251888], "abc": [0.5, -0.0, 0.5], "species": [{"occu": 1, "element": "Ni"}], "properties": {"magmom": 1.429}}, {"label": "Ni", "xyz": [0.0, 0.0, 11.251888], "abc": [0.0, -0.0, 0.5], "species": [{"occu": 1, "element": "Ni"}], "properties": {"magmom": 1.427}}, {"label": "P", "xyz": [4.328768677499999, 5.427780841043528, 11.251888], "abc": [0.75, 0.66419334, 0.5], "species": [{"occu": 1, "element": "P"}], "properties": {"magmom": -0.013000000000000001}}, {"label": "P", "xyz": [1.4429228925, 2.744208418956471, 11.251888], "abc": [0.25, 0.33580666000000003, 0.5], "species": [{"occu": 1, "element": "P"}], "properties": {"magmom": -0.013000000000000001}}, {"label": "O", "xyz": [1.4429228925, 3.630970994932759, 10.01391860108512], "abc": [0.25, 0.44431911, 0.44498837], "species": [{"occu": 1, "element": "O"}], "properties": {"magmom": 0.20500000000000002}}, {"label": "O", "xyz": [1.4429228925, 3.630970994932759, 12.489857398914879], "abc": [0.25, 0.44431911, 0.55501163], "species": [{"occu": 1, "element": "O"}], "properties": {"magmom": 0.20500000000000002}}, {"label": "O", "xyz": [4.328768677499999, 4.541018265067241, 12.489857398914879], "abc": [0.75, 0.55568089, 0.55501163], "species": [{"occu": 1, "element": "O"}], "properties": {"magmom": 0.20500000000000002}}, {"label": "O", "xyz": [4.328768677499999, 4.541018265067241, 10.01391860108512], "abc": [0.75, 0.55568089, 0.44498837], "species": [{"occu": 1, "element": "O"}], "properties": {"magmom": 0.20500000000000002}}, {"label": "O", "xyz": [2.718612060663732, 1.79833269630937, 11.251888], "abc": [0.47102518, 0.22006058, 0.5], "species": [{"occu": 1, "element": "O"}], "properties": {"magmom": 0.055}}, {"label": "O", "xyz": [3.053079509336267, 6.37365656369063, 11.251888], "abc": [0.52897482, 0.77993942, 0.5], "species": [{"occu": 1, "element": "O"}], "properties": {"magmom": 0.055}}, {"label": "O", "xyz": [5.604457845663733, 6.37365656369063, 11.251888], "abc": [0.97102518, 0.77993942, 0.5], "species": [{"occu": 1, "element": "O"}], "properties": {"magmom": 0.061}}, {"label": "O", "xyz": [0.16723372433626701, 1.79833269630937, 11.251888], "abc": [0.028974820000000002, 0.22006058, 0.5], "species": [{"occu": 1, "element": "O"}], "properties": {"magmom": 0.061}}], "@class": "Structure", "@module": "pymatgen.core.structure"}