{"lattice": {"a": 3.34844677, "c": 23.377978, "b": 6.39123287, "matrix": [[3.34844677, -0.0, 0.0], [0.0, 6.39123287, 0.0], [0.0, 0.0, 23.377978]], "volume": 500.30516531815783, "beta": 90.0, "alpha": 90.0, "gamma": 90.0}, "sites": [{"label": "Sm", "xyz": [1.674223385, 0.0, 11.688989], "abc": [0.5, 0.0, 0.5], "species": [{"occu": 1, "element": "Sm"}], "properties": {"magmom": 0.0}}, {"label": "Si", "xyz": [0.0, 4.391163715190964, 10.12133473461136], "abc": [0.0, 0.68706051, 0.43294312], "species": [{"occu": 1, "element": "Si"}], "properties": {"magmom": -0.0}}, {"label": "Si", "xyz": [0.0, 2.000075546041906, 13.25664326538864], "abc": [-0.0, 0.31294049, 0.56705688], "species": [{"occu": 1, "element": "Si"}], "properties": {"magmom": -0.0}}, {"label": "Si", "xyz": [0.0, 4.391163715190964, 13.25664326538864], "abc": [-0.0, 0.68706051, 0.56705688], "species": [{"occu": 1, "element": "Si"}], "properties": {"magmom": -0.0}}, {"label": "Si", "xyz": [0.0, 2.000075546041906, 10.12133473461136], "abc": [-0.0, 0.31294049, 0.43294312], "species": [{"occu": 1, "element": "Si"}], "properties": {"magmom": -0.0}}, {"label": "Si", "xyz": [1.674223385, 3.195616435, 11.688989], "abc": [0.5, 0.5, 0.5], "species": [{"occu": 1, "element": "Si"}], "properties": {"magmom": 0.0}}], "@class": "Structure", "@module": "pymatgen.core.structure"}