{"lattice": {"a": 3.66794457, "c": 26.432177, "b": 11.71743795, "matrix": [[3.66794457, 0.0, 0.0], [0.0, 11.71743795, 0.0], [0.0, 0.0, 26.432177]], "volume": 1136.0262331200613, "beta": 90.0, "alpha": 90.0, "gamma": 90.0}, "sites": [{"label": "Mn", "xyz": [0.0, 4.037429552935905, 13.531244368484629], "abc": [0.0, 0.3445659, 0.51192319], "species": [{"occu": 1, "element": "Mn"}], "properties": {"magmom": 3.198}}, {"label": "Mn", "xyz": [1.8339722850000002, 1.821289422064095, 12.90093263151537], "abc": [0.5, 0.1554341, 0.48807681], "species": [{"occu": 1, "element": "Mn"}], "properties": {"magmom": 3.198}}, {"label": "Mn", "xyz": [1.8339722850000002, 9.896148527935905, 12.90093263151537], "abc": [0.5, 0.8445659, 0.48807681], "species": [{"occu": 1, "element": "Mn"}], "properties": {"magmom": 3.198}}, {"label": "Mn", "xyz": [0.0, 7.680008397064095, 13.531244368484629], "abc": [-0.0, 0.6554341, 0.51192319], "species": [{"occu": 1, "element": "Mn"}], "properties": {"magmom": 3.198}}, {"label": "Zn", "xyz": [0.0, 5.858718975, 15.567979732046181], "abc": [0.0, 0.5, 0.58897834], "species": [{"occu": 1, "element": "Zn"}], "properties": {"magmom": 0.013000000000000001}}, {"label": "Zn", "xyz": [1.8339722850000002, 0.0, 10.86419726795382], "abc": [0.5, 0.0, 0.41102166], "species": [{"occu": 1, "element": "Zn"}], "properties": {"magmom": 0.013000000000000001}}, {"label": "O", "xyz": [1.8339722850000002, 0.0, 13.20449614013311], "abc": [0.5, 0.0, 0.49956143000000003], "species": [{"occu": 1, "element": "O"}], "properties": {"magmom": -0.074}}, {"label": "O", "xyz": [0.0, 5.858718975, 13.22768085986689], "abc": [0.0, 0.5, 0.50043857], "species": [{"occu": 1, "element": "O"}], "properties": {"magmom": -0.074}}, {"label": "O", "xyz": [0.0, 9.622357349529272, 13.32736955110062], "abc": [0.0, 0.82119977, 0.50421006], "species": [{"occu": 1, "element": "O"}], "properties": {"magmom": -0.116}}, {"label": "O", "xyz": [1.8339722850000002, 7.953799575470729, 13.104807448899379], "abc": [0.5, 0.67880023, 0.49578994], "species": [{"occu": 1, "element": "O"}], "properties": {"magmom": -0.116}}, {"label": "O", "xyz": [1.8339722850000002, 3.763638374529272, 13.104807448899379], "abc": [0.5, 0.32119977, 0.49578994], "species": [{"occu": 1, "element": "O"}], "properties": {"magmom": -0.116}}, {"label": "O", "xyz": [0.0, 2.095080600470728, 13.32736955110062], "abc": [0.0, 0.17880023, 0.50421006], "species": [{"occu": 1, "element": "O"}], "properties": {"magmom": -0.116}}, {"label": "O", "xyz": [0.0, 4.065324788765952, 15.352596080474598], "abc": [0.0, 0.34694656, 0.5808298], "species": [{"occu": 1, "element": "O"}], "properties": {"magmom": -0.094}}, {"label": "O", "xyz": [1.8339722850000002, 1.7933941862340481, 11.0795809195254], "abc": [0.5, 0.15305344, 0.4191702], "species": [{"occu": 1, "element": "O"}], "properties": {"magmom": -0.094}}, {"label": "O", "xyz": [0.0, 7.652113161234048, 15.352596080474598], "abc": [0.0, 0.65305344, 0.5808298], "species": [{"occu": 1, "element": "O"}], "properties": {"magmom": -0.094}}, {"label": "O", "xyz": [1.8339722850000002, 9.924043763765953, 11.0795809195254], "abc": [0.5, 0.84694656, 0.4191702], "species": [{"occu": 1, "element": "O"}], "properties": {"magmom": -0.094}}], "@class": "Structure", "@module": "pymatgen.core.structure"}