{"lattice": {"a": 4.11561183, "c": 26.757509, "b": 4.11312567, "matrix": [[4.11561183, 0.0, 0.0], [0.0, 4.11312567, 0.0], [0.0, 0.0, 26.757509]], "volume": 452.951879375493, "beta": 90.0, "alpha": 90.0, "gamma": 90.0}, "sites": [{"label": "Tb", "xyz": [0.0, 2.056562835, 10.90846835738393], "abc": [-0.0, 0.5, 0.40767877], "species": [{"occu": 1, "element": "Tb"}], "properties": {"magmom": -0.0}}, {"label": "Tb", "xyz": [2.057805915, 0.0, 15.849040642616071], "abc": [0.5, -0.0, 0.59232123], "species": [{"occu": 1, "element": "Tb"}], "properties": {"magmom": 0.0}}, {"label": "Co", "xyz": [0.0, 2.056562835, 14.478529058888771], "abc": [0.0, 0.5, 0.54110153], "species": [{"occu": 1, "element": "Co"}], "properties": {"magmom": 0.0}}, {"label": "Co", "xyz": [2.057805915, 0.0, 12.27897994111123], "abc": [0.5, -0.0, 0.45889847], "species": [{"occu": 1, "element": "Co"}], "properties": {"magmom": -0.0}}, {"label": "Ge", "xyz": [0.0, 2.056562835, 16.73146636407365], "abc": [0.0, 0.5, 0.62529985], "species": [{"occu": 1, "element": "Ge"}], "properties": {"magmom": 0.0}}, {"label": "Ge", "xyz": [2.057805915, 0.0, 10.02604263592635], "abc": [0.5, 0.0, 0.37470015], "species": [{"occu": 1, "element": "Ge"}], "properties": {"magmom": -0.0}}, {"label": "Ge", "xyz": [2.057805915, 2.056562835, 13.38048811900811], "abc": [0.5, 0.5, 0.50006479], "species": [{"occu": 1, "element": "Ge"}], "properties": {"magmom": -0.0}}, {"label": "Ge", "xyz": [0.0, 0.0, 13.37702088099189], "abc": [-0.0, 0.0, 0.49993521], "species": [{"occu": 1, "element": "Ge"}], "properties": {"magmom": 0.0}}], "@class": "Structure", "@module": "pymatgen.core.structure"}