{"lattice": {"a": 3.7446612, "c": 26.313777, "b": 3.744661002748928, "matrix": [[3.7446612, 0.0, 0.0], [1.8723306, 3.2429715, 0.0], [0.0, 0.0, 26.313777]], "volume": 319.5500226719708, "beta": 90.0, "alpha": 90.0, "gamma": 59.99999825751571}, "sites": [{"label": "Zr", "xyz": [3.7446630723306003, 2.1619820809905, 14.414418376936833], "abc": [0.666667, 0.666667, 0.54778979], "species": [{"occu": 1, "element": "Zr"}], "properties": {"magmom": 0.0}}, {"label": "Zr", "xyz": [1.872328727669399, 1.0809894190095, 11.89935862306317], "abc": [0.333333, 0.333333, 0.45221021], "species": [{"occu": 1, "element": "Zr"}], "properties": {"magmom": 0.0}}, {"label": "Br", "xyz": [0.0, 0.0, 16.30896874516917], "abc": [-0.0, 0.0, 0.6197882100000001], "species": [{"occu": 1, "element": "Br"}], "properties": {"magmom": 0.0}}, {"label": "Br", "xyz": [0.0, 0.0, 10.00480825483083], "abc": [-0.0, 0.0, 0.38021179], "species": [{"occu": 1, "element": "Br"}], "properties": {"magmom": 0.0}}, {"label": "O", "xyz": [3.7446630723306003, 2.1619820809905, 12.212709394885652], "abc": [0.666667, 0.666667, 0.46411845], "species": [{"occu": 1, "element": "O"}], "properties": {"magmom": -0.0}}, {"label": "O", "xyz": [1.872328727669399, 1.0809894190095, 14.101067605114352], "abc": [0.333333, 0.333333, 0.53588155], "species": [{"occu": 1, "element": "O"}], "properties": {"magmom": -0.0}}], "@class": "Structure", "@module": "pymatgen.core.structure"}