{"lattice": {"a": 3.50632322, "c": 27.221538, "b": 3.50632322, "matrix": [[3.50632322, 0.0, -0.0], [-0.0, 3.50632322, 0.0], [0.0, 0.0, 27.221538]], "volume": 334.66982331636655, "beta": 90.0, "alpha": 90.0, "gamma": 90.0}, "sites": [{"label": "Nb", "xyz": [0.0, 1.75316161, 12.659493571728781], "abc": [-0.0, 0.5, 0.46505431], "species": [{"occu": 1, "element": "Nb"}], "properties": {"magmom": -0.0}}, {"label": "Nb", "xyz": [1.75316161, 0.0, 8.01648950848122], "abc": [0.5, -0.0, 0.29449069], "species": [{"occu": 1, "element": "Nb"}], "properties": {"magmom": -0.0}}, {"label": "Nb", "xyz": [1.75316161, 0.0, 11.08687537777698], "abc": [0.5, -0.0, 0.40728321], "species": [{"occu": 1, "element": "Nb"}], "properties": {"magmom": -0.0}}, {"label": "Nb", "xyz": [0.0, 1.75316161, 9.589080480895019], "abc": [-0.0, 0.5, 0.35226079], "species": [{"occu": 1, "element": "Nb"}], "properties": {"magmom": -0.0}}, {"label": "Te", "xyz": [1.75316161, 0.0, 14.14748762606922], "abc": [0.5, 0.0, 0.51971669], "species": [{"occu": 1, "element": "Te"}], "properties": {"magmom": 0.0}}, {"label": "Te", "xyz": [0.0, 1.75316161, 6.528468232602779], "abc": [-0.0, 0.5, 0.23982731000000002], "species": [{"occu": 1, "element": "Te"}], "properties": {"magmom": 0.0}}], "@class": "Structure", "@module": "pymatgen.core.structure"}