{"lattice": {"a": 3.70266775, "c": 22.945086, "b": 7.60992406, "matrix": [[3.70266775, -0.0, 0.0], [0.0, 7.60992406, 0.0], [0.0, 0.0, 22.945086]], "volume": 646.5241562308785, "beta": 90.0, "alpha": 90.0, "gamma": 90.0}, "sites": [{"label": "Al", "xyz": [1.851333875, 3.80496203, 11.472543], "abc": [0.5, 0.5, 0.5], "species": [{"occu": 1, "element": "Al"}], "properties": {"magmom": -0.003}}, {"label": "Cr", "xyz": [1.851333875, 0.0, 11.472543], "abc": [0.5, -0.0, 0.5], "species": [{"occu": 1, "element": "Cr"}], "properties": {"magmom": 3.923}}, {"label": "F", "xyz": [1.851333875, 3.80496203, 13.20512231374452], "abc": [0.5, 0.5, 0.5755098200000001], "species": [{"occu": 1, "element": "F"}], "properties": {"magmom": 0.091}}, {"label": "F", "xyz": [1.851333875, 3.80496203, 9.73996368625548], "abc": [0.5, 0.5, 0.42449018], "species": [{"occu": 1, "element": "F"}], "properties": {"magmom": 0.091}}, {"label": "F", "xyz": [1.851333875, 1.8820713508695612, 11.472543], "abc": [0.5, 0.24731802, 0.5], "species": [{"occu": 1, "element": "F"}], "properties": {"magmom": 0.017}}, {"label": "F", "xyz": [1.851333875, 5.727852709130438, 11.472543], "abc": [0.5, 0.75268198, 0.5], "species": [{"occu": 1, "element": "F"}], "properties": {"magmom": 0.017}}, {"label": "F", "xyz": [0.0, 3.80496203, 11.472543], "abc": [-0.0, 0.5, 0.5], "species": [{"occu": 1, "element": "F"}], "properties": {"magmom": 0.061}}], "@class": "Structure", "@module": "pymatgen.core.structure"}