{"lattice": {"a": 3.63389618, "c": 23.548695, "b": 5.91692391, "matrix": [[3.63389618, 0.0, 0.0], [0.0, 5.91692391, 0.0], [0.0, 0.0, 23.548695]], "volume": 506.331963975549, "beta": 90.0, "alpha": 90.0, "gamma": 90.0}, "sites": [{"label": "Be", "xyz": [1.81694809, 0.0, 0.0], "abc": [0.5, 0.0, -0.0], "species": [{"occu": 1, "element": "Be"}], "properties": {"magmom": -0.0}}, {"label": "Be", "xyz": [1.81694809, 2.958461955, 0.0], "abc": [0.5, 0.5, -0.0], "species": [{"occu": 1, "element": "Be"}], "properties": {"magmom": -0.0}}, {"label": "Br", "xyz": [1.81694809, 4.4376929325, 21.9026577035865], "abc": [0.5, 0.75, 0.9301007], "species": [{"occu": 1, "element": "Br"}], "properties": {"magmom": 0.0}}, {"label": "Br", "xyz": [0.0, 4.4376929325, 1.21494805662195], "abc": [-0.0, 0.75, 0.05159301], "species": [{"occu": 1, "element": "Br"}], "properties": {"magmom": 0.0}}, {"label": "Br", "xyz": [1.81694809, 1.4792309775, 1.6460372964135002], "abc": [0.5, 0.25, 0.0698993], "species": [{"occu": 1, "element": "Br"}], "properties": {"magmom": 0.0}}, {"label": "Br", "xyz": [0.0, 1.4792309775, 22.33374694337805], "abc": [0.0, 0.25, 0.9484069900000001], "species": [{"occu": 1, "element": "Br"}], "properties": {"magmom": 0.0}}], "@class": "Structure", "@module": "pymatgen.core.structure"}