{"lattice": {"a": 4.75465312, "c": 24.520602, "b": 7.46366431, "matrix": [[4.75465312, -0.0, 0.0], [-0.0, 7.46366431, 0.0], [0.0, 0.0, 24.520602]], "volume": 870.1659085063787, "beta": 90.0, "alpha": 90.0, "gamma": 90.0}, "sites": [{"label": "As", "xyz": [2.37732656, 3.731832155, 14.09926130871708], "abc": [0.5, 0.5, 0.57499654], "species": [{"occu": 1, "element": "As"}], "properties": {"magmom": 0.006}}, {"label": "As", "xyz": [0.0, 0.0, 14.09926130871708], "abc": [-0.0, -0.0, 0.57499654], "species": [{"occu": 1, "element": "As"}], "properties": {"magmom": 0.009000000000000001}}, {"label": "As", "xyz": [2.37732656, 3.731832155, 10.42134069128292], "abc": [0.5, 0.5, 0.42500346], "species": [{"occu": 1, "element": "As"}], "properties": {"magmom": 0.006}}, {"label": "As", "xyz": [0.0, 0.0, 10.42134069128292], "abc": [-0.0, -0.0, 0.42500346], "species": [{"occu": 1, "element": "As"}], "properties": {"magmom": 0.009000000000000001}}, {"label": "As", "xyz": [1.404515260074416, 0.7979594583627331, 12.260301], "abc": [0.29539805, 0.10691256, 0.5], "species": [{"occu": 1, "element": "As"}], "properties": {"magmom": -0.004}}, {"label": "As", "xyz": [3.350137859925584, 6.665704851637266, 12.260301], "abc": [0.70460195, 0.8930874400000001, 0.5], "species": [{"occu": 1, "element": "As"}], "properties": {"magmom": -0.004}}, {"label": "As", "xyz": [0.9728112999255841, 4.529791613362734, 12.260301], "abc": [0.20460195, 0.60691256, 0.5], "species": [{"occu": 1, "element": "As"}], "properties": {"magmom": -0.004}}, {"label": "As", "xyz": [3.781841820074416, 2.933872696637266, 12.260301], "abc": [0.79539805, 0.39308744, 0.5], "species": [{"occu": 1, "element": "As"}], "properties": {"magmom": -0.004}}], "@class": "Structure", "@module": "pymatgen.core.structure"}