{"lattice": {"a": 3.61872184, "c": 28.1072580897433, "b": 5.817922143374249, "matrix": [[3.61872184, 0.0, 0.0], [0.0, 5.81746866, -0.07263922], [0.0, 0.22541649, 28.10635417]], "volume": 591.74862506154, "beta": 90.0, "alpha": 90.25587114613015, "gamma": 90.0}, "sites": [{"label": "Os", "xyz": [1.80936092, 5.151380691745144, 8.458703586794718], "abc": [0.5, 0.8737531900000001, 0.30321159000000003], "species": [{"occu": 1, "element": "Os"}], "properties": {"magmom": -0.0}}, {"label": "Os", "xyz": [0.0, 2.622114979642599, 8.592211096030226], "abc": [-0.0, 0.43884185000000003, 0.30683767], "species": [{"occu": 1, "element": "Os"}], "properties": {"magmom": 0.0}}, {"label": "Os", "xyz": [1.80936092, 5.264968776802513, 5.630957548167315], "abc": [0.5, 0.8971745999999999, 0.20266334], "species": [{"occu": 1, "element": "Os"}], "properties": {"magmom": 0.0}}, {"label": "Os", "xyz": [0.0, 2.098621969177488, 5.718145597025224], "abc": [-0.0, 0.35282634, 0.20435858], "species": [{"occu": 1, "element": "Os"}], "properties": {"magmom": -0.0}}, {"label": "Os", "xyz": [1.80936092, 4.741288783700096, 2.756588556145001], "abc": [0.5, 0.81112737, 0.10017337], "species": [{"occu": 1, "element": "Os"}], "properties": {"magmom": 0.0}}, {"label": "Os", "xyz": [0.0, 2.212159927419933, 2.890243054047459], "abc": [-0.0, 0.37623935000000003, 0.10380474], "species": [{"occu": 1, "element": "Os"}], "properties": {"magmom": -0.0}}, {"label": "S", "xyz": [1.80936092, 3.356879462524122, 9.913635199695117], "abc": [0.5, 0.56331076, 0.35417449], "species": [{"occu": 1, "element": "S"}], "properties": {"magmom": 0.0}}, {"label": "S", "xyz": [0.0, 0.43539966733852203, 9.595083908892786], "abc": [0.0, 0.06160927, 0.34154409], "species": [{"occu": 1, "element": "S"}], "properties": {"magmom": 0.0}}, {"label": "S", "xyz": [1.80936092, 3.134739585931057, 4.605328209536697], "abc": [0.5, 0.53244706, 0.16522971], "species": [{"occu": 1, "element": "S"}], "properties": {"magmom": -0.0}}, {"label": "S", "xyz": [0.0, 0.14279140039871502, 4.129513225811551], "abc": [0.0, 0.018850330000000002, 0.14697326], "species": [{"occu": 1, "element": "S"}], "properties": {"magmom": 0.0}}, {"label": "S", "xyz": [1.80936092, 1.403532269200523, 7.292706445839582], "abc": [0.5, 0.2311846, 0.26006573], "species": [{"occu": 1, "element": "S"}], "properties": {"magmom": 0.0}}, {"label": "S", "xyz": [0.0, 4.228807078631818, 6.74353796359745], "abc": [0.0, 0.71754663, 0.24178376000000001], "species": [{"occu": 1, "element": "S"}], "properties": {"magmom": -0.0}}, {"label": "S", "xyz": [0.0, 4.006857977384879, 1.43531095120704], "abc": [-0.0, 0.68671561, 0.05284191], "species": [{"occu": 1, "element": "S"}], "properties": {"magmom": 0.0}}, {"label": "S", "xyz": [1.80936092, 1.110602781142162, 1.826714200836802], "abc": [0.5, 0.18837103, 0.06547976], "species": [{"occu": 1, "element": "S"}], "properties": {"magmom": 0.0}}], "@class": "Structure", "@module": "pymatgen.core.structure"}