{"lattice": {"a": 3.404534, "c": 27.012983389876357, "b": 11.452687603037683, "matrix": [[3.404534, 0.0, 0.0], [0.0, 11.439018, -0.559393], [0.0, 0.219694, 27.01209]], "volume": 1052.3914346000774, "beta": 90.0, "alpha": 92.33367242518518, "gamma": 90.0}, "sites": [{"label": "Ta", "xyz": [2.5534005, 0.744852391972, 6.995970260529], "abc": [0.75, 0.060117, 0.260239], "species": [{"occu": 1, "element": "Ta"}], "properties": {"magmom": 0.0}}, {"label": "Ta", "xyz": [0.8511335, 10.837104456166001, 10.019431819901001], "abc": [0.25, 0.9398829999999999, 0.39038799999999996], "species": [{"occu": 1, "element": "Ta"}], "properties": {"magmom": 0.0}}, {"label": "Ta", "xyz": [2.5534005, 7.634383338062, 7.9400475283], "abc": [0.75, 0.66149, 0.307643], "species": [{"occu": 1, "element": "Ta"}], "properties": {"magmom": 0.0}}, {"label": "Ta", "xyz": [0.8511335, 3.94757372977, 9.07538156422], "abc": [0.25, 0.33851000000000003, 0.342985], "species": [{"occu": 1, "element": "Ta"}], "properties": {"magmom": 0.0}}, {"label": "S", "xyz": [2.5534005, 10.257618678618, 8.192328146941], "abc": [0.75, 0.890543, 0.321726], "species": [{"occu": 1, "element": "S"}], "properties": {"magmom": -0.0}}, {"label": "S", "xyz": [0.8511335, 1.324326950196, 8.823101504972001], "abc": [0.25, 0.109456, 0.32890199999999997], "species": [{"occu": 1, "element": "S"}], "properties": {"magmom": -0.0}}, {"label": "S", "xyz": [2.5534005, 1.014756341644, 11.569708196744], "abc": [0.75, 0.080452, 0.429982], "species": [{"occu": 1, "element": "S"}], "properties": {"magmom": -0.0}}, {"label": "S", "xyz": [0.8511335, 10.567200726188, 5.445720895776001], "abc": [0.25, 0.9195479999999999, 0.22064599999999998], "species": [{"occu": 1, "element": "S"}], "properties": {"magmom": -0.0}}, {"label": "S", "xyz": [0.8511335, 5.907145408474001, 7.268522450454], "abc": [0.25, 0.5110319999999999, 0.279667], "species": [{"occu": 1, "element": "S"}], "properties": {"magmom": -0.0}}, {"label": "S", "xyz": [2.5534005, 5.674811659358001, 9.746906642066], "abc": [0.75, 0.48896799999999996, 0.370961], "species": [{"occu": 1, "element": "S"}], "properties": {"magmom": -0.0}}, {"label": "S", "xyz": [0.8511335, 8.227788167298002, 9.728206196928], "abc": [0.25, 0.712074, 0.374889], "species": [{"occu": 1, "element": "S"}], "properties": {"magmom": -0.0}}, {"label": "S", "xyz": [2.5534005, 3.35416868084, 7.287195883502], "abc": [0.75, 0.28792599999999996, 0.275738], "species": [{"occu": 1, "element": "S"}], "properties": {"magmom": -0.0}}, {"label": "S", "xyz": [0.8511335, 1.586857078608, 5.431165967496001], "abc": [0.25, 0.13480799999999998, 0.20385599999999998], "species": [{"occu": 1, "element": "S"}], "properties": {"magmom": -0.0}}, {"label": "S", "xyz": [2.5534005, 9.995099989224, 11.584263125024], "abc": [0.75, 0.865192, 0.446772], "species": [{"occu": 1, "element": "S"}], "properties": {"magmom": -0.0}}, {"label": "S", "xyz": [0.8511335, 8.397071270887999, 6.20622990917], "abc": [0.25, 0.7293700000000001, 0.244862], "species": [{"occu": 1, "element": "S"}], "properties": {"magmom": -0.0}}, {"label": "S", "xyz": [2.5534005, 3.184885796944, 10.809199183350001], "abc": [0.75, 0.27063000000000004, 0.40576599999999996], "species": [{"occu": 1, "element": "S"}], "properties": {"magmom": -0.0}}], "@class": "Structure", "@module": "pymatgen.core.structure"}